{
  "package": {
    "path": [
      "foo"
    ]
  },
  "imports": [
    {
      "path": "interface.m4",
      "span": [
        14,
        36
      ]
    }
  ],
  "groups": [
    {
      "inner": {
        "Specification": {
          "Cno": {
            "declaration": {
              "name": {
                "name": "FooHttpResponse",
                "span": [
                  42,
                  57
                ]
              },
              "type_": {
                "Path": [
                  [
                    "common",
                    "HttpResponse"
                  ],
                  {
                    "span": [
                      59,
                      79
                    ]
                  }
                ]
              }
            },
            "fields": [
              {
                "Action": {
                  "name": {
                    "name": "get_status",
                    "span": [
                      93,
                      103
                    ]
                  },
                  "type_": {
                    "Function": [
                      {
                        "self_": {
                          "placement": null,
                          "mutability": "Const"
                        },
                        "args": [],
                        "ret": {
                          "Numeric": [
                            "U16",
                            {
                              "span": [
                                129,
                                132
                              ]
                            }
                          ]
                        }
                      },
                      {
                        "span": [
                          105,
                          132
                        ]
                      }
                    ]
                  }
                }
              }
            ]
          }
        }
      }
    },
    {
      "inner": {
        "Specification": {
          "State": {
            "declaration": {
              "name": {
                "name": "FooCounter",
                "span": [
                  143,
                  153
                ]
              },
              "type_": {
                "Path": [
                  [
                    "common",
                    "Counter"
                  ],
                  {
                    "span": [
                      155,
                      170
                    ]
                  }
                ]
              }
            },
            "fields": [
              {
                "Selector": {
                  "name": {
                    "name": "name",
                    "span": [
                      186,
                      190
                    ]
                  },
                  "type_": {
                    "String": {
                      "span": [
                        192,
                        198
                      ]
                    }
                  }
                }
              },
              {
                "Action": {
                  "name": {
                    "name": "increment",
                    "span": [
                      212,
                      221
                    ]
                  },
                  "type_": {
                    "Function": [
                      {
                        "self_": null,
                        "args": [],
                        "ret": {
                          "Empty": {
                            "span": [
                              234,
                              234
                            ]
                          }
                        }
                      },
                      {
                        "span": [
                          223,
                          233
                        ]
                      }
                    ]
                  }
                }
              }
            ]
          }
        }
      }
    }
  ]
}